hivemind_chatroom/__init__.py
hivemind_chatroom/__main__.py
hivemind_chatroom/version.py
hivemind_flask_chatroom-0.1.0.dist-info/LICENSE
hivemind_flask_chatroom-0.1.0.dist-info/METADATA
hivemind_flask_chatroom-0.1.0.dist-info/WHEEL
hivemind_flask_chatroom-0.1.0.dist-info/entry_points.txt
hivemind_flask_chatroom-0.1.0.dist-info/top_level.txt
hivemind_flask_chatroom-0.1.0.dist-info/RECORD
