Metadata-Version: 2.1
Name: hivemind-flask-chatroom
Version: 0.1.0
Summary: Hivemind OVOS Chatroom
Home-page: https://github.com/JarbasHiveMind/hivemind-flask-chatroom
Author: jarbasAI
Author-email: jarbasai@mailfence.com
License: Apache2.0
License-File: LICENSE
Requires-Dist: hivemind-bus-client
Requires-Dist: flask
